{"trial_id": "3", "hyperparameters": {"space": [{"class_name": "Choice", "config": {"name": "optimizer", "default": "Adam", "conditions": [], "values": ["Adam", "rmsprop", "adagrad", "sgd"], "ordered": false}}], "values": {"optimizer": "Adam"}}, "metrics": {"metrics": {"accuracy": {"direction": "max", "observations": [{"value": [0.7475569844245911], "step": 3}]}, "loss": {"direction": "min", "observations": [{"value": [0.5179308652877808], "step": 3}]}, "val_accuracy": {"direction": "max", "observations": [{"value": [0.8181818127632141], "step": 3}]}, "val_loss": {"direction": "min", "observations": [{"value": [0.5178995728492737], "step": 3}]}}}, "score": 0.8181818127632141, "best_step": 3, "status": "COMPLETED", "message": null}